cyclicprng.py
cyclicprng-0.2.0.dist-info/LICENSE
cyclicprng-0.2.0.dist-info/METADATA
cyclicprng-0.2.0.dist-info/WHEEL
cyclicprng-0.2.0.dist-info/top_level.txt
cyclicprng-0.2.0.dist-info/RECORD
