Metadata-Version: 2.1
Name: cyclicprng
Version: 0.2.0
Summary: A simple cyclic PRNG
License: Apache License
Project-URL: Source Code, https://github.com/natlas/cyclicprng
Project-URL: Tracker, https://github.com/natlas/cyclicprng/issues
Classifier: License :: OSI Approved :: Apache Software License
Classifier: Programming Language :: Python :: 3
Classifier: Programming Language :: Python :: 3.10
Classifier: Programming Language :: Python :: 3.11
Classifier: Programming Language :: Python :: 3.8
Classifier: Programming Language :: Python :: 3.9
Requires-Python: >=3.8
License-File: LICENSE
Requires-Dist: sympy
